modgeosys/__init__.py
modgeosys/graph/__init__.py
modgeosys/graph/steiner.py
tests/modgeosys/graph/cuda/conftest.py
modgeosys_fast_graph_algorithms-0.3.5.dist-info/LICENSE
modgeosys_fast_graph_algorithms-0.3.5.dist-info/METADATA
modgeosys_fast_graph_algorithms-0.3.5.dist-info/WHEEL
modgeosys_fast_graph_algorithms-0.3.5.dist-info/RECORD
