Metadata-Version: 2.1
Name: modgeosys-fast-graph-algorithms
Version: 0.3.5
Summary: 
Author: Kevin Weller
Author-email: klweller@icloud.com
Requires-Python: >=3.11.9,<4.0.0
Classifier: Programming Language :: Python :: 3
Classifier: Programming Language :: Python :: 3.12
Requires-Dist: cualgo (>=0.2.0,<0.3.0)
Requires-Dist: matplotlib (>=3.9.2,<4.0.0)
Requires-Dist: mpld3 (>=0.5.10,<0.6.0)
Requires-Dist: networkx (>=3.3,<4.0)
Requires-Dist: numpy (>=1.26.4,<2.0.0)
Requires-Dist: pandas (>=2.2.2,<3.0.0)
Requires-Dist: scipy (>=1.14.1,<2.0.0)
